LICENSE
README.md
pyproject.toml
agentpay_wallet/__init__.py
agentpay_wallet-0.0.1.dev0.dist-info/METADATA
agentpay_wallet-0.0.1.dev0.dist-info/WHEEL
agentpay_wallet-0.0.1.dev0.dist-info/licenses/LICENSE
agentpay_wallet-0.0.1.dev0.dist-info/RECORD
