Metadata-Version: 2.4
Name: agentpay-wallet
Version: 0.0.1.dev0
Summary: Reserved project name for future AgentPay Wallet.
Project-URL: Homepage, https://agentpay.me
Author-email: AgentPay <developers@agentpay.me>
License: This package is proprietary and not licensed for redistribution or reuse.
License-File: LICENSE
Keywords: agentpay,infrastructure,mcp,payments,wallet
Classifier: Development Status :: 1 - Planning
Classifier: License :: Other/Proprietary License
Classifier: Programming Language :: Python :: 3
Requires-Python: >=3.8
